sonata/__init__.py
sonata/config.py
sonata/iotools.py
sonata/utils.py
sonata/circuit/__init__.py
sonata/circuit/column_property.py
sonata/circuit/edge.py
sonata/circuit/file.py
sonata/circuit/file_root.py
sonata/circuit/group.py
sonata/circuit/node.py
sonata/circuit/population.py
sonata/circuit/types_table.py
sonata/circuit/utils.py
sonata/reports/__init__.py
sonata/reports/compartment/__init__.py
sonata/reports/compartment/compartment_reader.py
sonata/reports/compartment/compartment_report.py
sonata/reports/compartment/compartment_writer.py
sonata/reports/compartment/core.py
sonata/reports/ecp/__init__.py
sonata/reports/spike_trains/__init__.py
sonata/reports/spike_trains/core.py
sonata/reports/spike_trains/plotting.py
sonata/reports/spike_trains/spike_train_buffer.py
sonata/reports/spike_trains/spike_trains.py
sonata/reports/spike_trains/spike_trains_file.py
sonata/reports/spike_trains/stats.py
sonata/reports/spike_trains/adaptors/__init__.py
sonata/reports/spike_trains/adaptors/csv_adaptors.py
sonata/reports/spike_trains/adaptors/nwb_adaptors.py
sonata/reports/spike_trains/adaptors/sonata_adaptors.py
sonata/tests/__init__.py
sonata/tests/test_mock.py
sonata-0.0.2.dist-info/METADATA
sonata-0.0.2.dist-info/WHEEL
sonata-0.0.2.dist-info/top_level.txt
sonata-0.0.2.dist-info/RECORD
