Metadata-Version: 2.1
Name: sonata
Version: 0.0.2
Summary: SONATA Data Format API
Home-page: https://github.com/AllenInstitute/sonata
License: UNKNOWN
Keywords: neuroscience,scientific,modeling,networks,simulation
Platform: any
Classifier: Development Status :: 2 - Pre-Alpha
Classifier: Intended Audience :: Science/Research
Classifier: License :: OSI Approved :: BSD License
Classifier: Natural Language :: English
Classifier: Operating System :: OS Independent
Classifier: Programming Language :: Python :: 2.7
Classifier: Programming Language :: Python :: 3.6
Classifier: Topic :: Scientific/Engineering :: Medical Science Apps.
Classifier: Topic :: Scientific/Engineering :: Bio-Informatics
Classifier: Topic :: Scientific/Engineering :: Artificial Intelligence
Requires-Dist: jsonschema
Requires-Dist: pandas
Requires-Dist: numpy
Requires-Dist: six
Requires-Dist: h5py
